etl_db_tools/__init__.py
etl_db_tools/base/connection.py
etl_db_tools/base/schema.py
etl_db_tools/sqlservertools/sqlservertools.py
etl_db_tools/templates/create_table.sql
etl_db_tools/templates/finalize_copy.sql
etl_db_tools/templates/find_tables.sql
etl_db_tools/templates/insert.sql
etl_db_tools-0.2.2.dist-info/WHEEL
etl_db_tools-0.2.2.dist-info/METADATA
etl_db_tools-0.2.2.dist-info/RECORD
