Metadata-Version: 2.3
Name: etl-db-tools
Version: 0.2.2
Summary: tools for moving data
Author: Niels
Author-email: Niels <niels.kakes@gmail.com>
Requires-Dist: pyodbc>=5.2.0,<6.0.0
Requires-Dist: tomli>=2.1.0,<3.0.0
Requires-Dist: jinja2>=3.1.4,<4.0.0
Requires-Python: >=3.10, <4.0
